fugassem/__init__.py
fugassem/config.py
fugassem/fugassem.py
fugassem/utilities.py
fugassem/common/__init__.py
fugassem/common/corrmp.py
fugassem/common/dictation.py
fugassem/common/extract_feature_subset.py
fugassem/common/format_function.py
fugassem/common/geneontology.py
fugassem/common/table2.py
fugassem/common/table2_stats.py
fugassem/common/transpose.py
fugassem/common/utils.py
fugassem/data/GO/go-basic.obo
fugassem/data/GO/go.obo.gz
fugassem/predict/__init__.py
fugassem/predict/collect_ml_results.py
fugassem/predict/machine_learning.py
fugassem/predict/merged_prediction.py
fugassem/predict/predict_function.py
fugassem/predict/prepare_nextlayer_ml.py
fugassem/predict/select_feature.py
fugassem/preprocess/__init__.py
fugassem/preprocess/build_union_terms.py
fugassem/preprocess/calculate_correlation.py
fugassem/preprocess/collect_features.py
fugassem/preprocess/convert_coann.py
fugassem/preprocess/impute_nan.py
fugassem/preprocess/refine_abunds.py
fugassem/preprocess/refine_anns.py
fugassem/preprocess/split_taxa.py
fugassem/tasks/__init__.py
fugassem/tasks/fugassem_prediction.py
fugassem/tasks/fugassem_preprocessing.py
fugassem/tasks/fugassem_process.py
fugassem/tools/__init__.py
fugassem/tools/abundance_RPK.py
fugassem/tools/abundance_normalization.py
fugassem/tools/abundance_smoothing.py
fugassem/tools/collect_seqSimilarity_results.py
fugassem/tools/extract_feature_subset.py
fugassem/tools/gene_abundance.py
fugassem/tools/gene_abundance_indexRef.py
fugassem/tools/gene_catalog_abundance.py
fugassem/tools/generate_annotation_input.py
fugassem/tools/generate_stratified_mtx_input.py
fugassem/tools/performance_vis.py
fugassem/tools/prepare_annotation.py
fugassem/tools/prepare_coann_pairs.py
fugassem/tools/prepare_contig.py
fugassem/tools/prepare_seqSimilarity.py
fugassem/tools/stratified_abundance.py
fugassem/tools/sum_to_family_abundance.py
fugassem/workflows/fugassem_workflow.py
fugassem-0.3.8.data/scripts/fugassem_workflow.py
fugassem-0.3.8.dist-info/licenses/LICENSE
fugassem-0.3.8.dist-info/METADATA
fugassem-0.3.8.dist-info/WHEEL
fugassem-0.3.8.dist-info/entry_points.txt
fugassem-0.3.8.dist-info/top_level.txt
fugassem-0.3.8.dist-info/RECORD
