Metadata-Version: 2.4
Name: fugassem
Version: 0.3.8
Summary: FUGAsseM: Function predictor of Uncharacterized Gene products by Assessing high-dimensional community data in microbiome
Home-page: https://github.com/biobakery/fugassem
Author: FUGAsseM Development Team
Author-email: zhangyc201211@gmail.com
License: MIT
Keywords: microbial,microbiome,bioinformatics,microbiology,metagenomic,metatranscriptomic,function prediction,unknown proteins,microbial dark matter,fugassem,anadama2
Platform: Linux
Platform: MacOS
Classifier: Programming Language :: Python
Classifier: Development Status :: 5 - Production/Stable
Classifier: Environment :: Console
Classifier: Operating System :: MacOS
Classifier: Operating System :: Unix
Classifier: Programming Language :: Python :: 3.7
Classifier: Topic :: Scientific/Engineering :: Bio-Informatics
License-File: LICENSE
Dynamic: author
Dynamic: author-email
Dynamic: classifier
Dynamic: description
Dynamic: home-page
Dynamic: keywords
Dynamic: license
Dynamic: license-file
Dynamic: platform
Dynamic: summary
